tsml/__init__.py
tsml/base.py
tsml/compose/__init__.py
tsml/compose/_channel_ensemble.py
tsml/compose/_sklearn_to_tsml.py
tsml/compose/tests/__init__.py
tsml/compose/tests/test_channel_ensemble.py
tsml/datasets/__init__.py
tsml/datasets/_data_io.py
tsml/datasets/EqualMinimalJapaneseVowels/EqualMinimalJapaneseVowels_TEST.ts
tsml/datasets/EqualMinimalJapaneseVowels/EqualMinimalJapaneseVowels_TRAIN.ts
tsml/datasets/MinimalChinatown/MinimalChinatown_TEST.ts
tsml/datasets/MinimalChinatown/MinimalChinatown_TRAIN.ts
tsml/datasets/MinimalGasPrices/MinimalGasPrices_TEST.ts
tsml/datasets/MinimalGasPrices/MinimalGasPrices_TRAIN.ts
tsml/datasets/MinimalJapaneseVowels/MinimalJapaneseVowels_TEST.ts
tsml/datasets/MinimalJapaneseVowels/MinimalJapaneseVowels_TRAIN.ts
tsml/datasets/UnequalMinimalChinatown/UnequalMinimalChinatown_TEST.ts
tsml/datasets/UnequalMinimalChinatown/UnequalMinimalChinatown_TRAIN.ts
tsml/datasets/UnequalMinimalGasPrices/UnequalMinimalGasPrices_TEST.ts
tsml/datasets/UnequalMinimalGasPrices/UnequalMinimalGasPrices_TRAIN.ts
tsml/datasets/tests/__init__.py
tsml/datasets/tests/test_data_io.py
tsml/dictionary_based/__init__.py
tsml/dictionary_based/_mrseql.py
tsml/dictionary_based/_mrsqm.py
tsml/distance_based/__init__.py
tsml/distance_based/_grail.py
tsml/dummy/__init__.py
tsml/dummy/_dummy.py
tsml/feature_based/__init__.py
tsml/feature_based/_fpca.py
tsml/interval_based/__init__.py
tsml/interval_based/_interval_pipelines.py
tsml/interval_based/tests/__init__.py
tsml/interval_based/tests/test_interval_pipelines.py
tsml/shapelet_based/__init__.py
tsml/shapelet_based/_rsf.py
tsml/tests/__init__.py
tsml/tests/test_all_estimators.py
tsml/tests/test_estimator_checks.py
tsml/tests/test_estimators_sklearn.py
tsml/tests/test_interface.py
tsml/tests/test_sklearn_compatability.py
tsml/transformations/__init__.py
tsml/transformations/_acf.py
tsml/transformations/_ar_coefficient.py
tsml/transformations/_fpca.py
tsml/transformations/_function_transformer.py
tsml-0.8.0.dist-info/licenses/LICENSE
tsml-0.8.0.dist-info/METADATA
tsml-0.8.0.dist-info/WHEEL
tsml-0.8.0.dist-info/top_level.txt
tsml-0.8.0.dist-info/RECORD
