Metadata-Version: 2.4
Name: tsml
Version: 0.8.0
Summary: A development sandbox for time series machine learning algorithms which dont fit into aeon.
Author-email: Matthew Middlehurst <m.b.middlehurst@soton.ac.uk>
Maintainer-email: Matthew Middlehurst <m.b.middlehurst@soton.ac.uk>
License: BSD 3-Clause License
Project-URL: homepage, https://www.timeseriesclassification.com/
Project-URL: repository, https://github.com/time-series-machine-learning/tsml-py/
Keywords: data-science,machine-learning,scikit-learn,time-series,time-series-classification,time-series-regression,time-series-clustering
Classifier: Intended Audience :: Science/Research
Classifier: License :: OSI Approved :: BSD License
Classifier: Topic :: Scientific/Engineering
Classifier: Operating System :: Microsoft :: Windows
Classifier: Operating System :: POSIX
Classifier: Operating System :: Unix
Classifier: Operating System :: MacOS
Classifier: Programming Language :: Python
Classifier: Programming Language :: Python :: 3.10
Classifier: Programming Language :: Python :: 3.11
Classifier: Programming Language :: Python :: 3.12
Classifier: Programming Language :: Python :: 3.13
Requires-Python: <3.14,>=3.10
License-File: LICENSE
Requires-Dist: aeon>=1.0.0
Requires-Dist: numba>=0.55.0
Requires-Dist: numpy>=1.21.0
Requires-Dist: scipy>=1.9.0
Requires-Dist: pandas>=1.5.3
Requires-Dist: scikit-learn>=1.0.0
Requires-Dist: packaging>=20.0
Provides-Extra: all-extras
Requires-Dist: grailts; extra == "all-extras"
Requires-Dist: scikit-fda>=0.7.0; (python_version > "3.9" and python_version < "3.13") and extra == "all-extras"
Requires-Dist: statsmodels>=0.12.1; extra == "all-extras"
Requires-Dist: wildboar<=1.2.0; extra == "all-extras"
Provides-Extra: unstable-extras
Requires-Dist: mrsqm>=0.0.7; (platform_system == "Linux" and python_version < "3.12") and extra == "unstable-extras"
Requires-Dist: mrseql<0.1.0,>=0.0.4; (platform_system == "Linux" and python_version < "3.12") and extra == "unstable-extras"
Provides-Extra: dev
Requires-Dist: pre-commit; extra == "dev"
Requires-Dist: pytest; extra == "dev"
Requires-Dist: pytest-randomly; extra == "dev"
Requires-Dist: pytest-timeout; extra == "dev"
Requires-Dist: pytest-xdist[psutil]; extra == "dev"
Requires-Dist: pytest-cov; extra == "dev"
Requires-Dist: pytest-rerunfailures; extra == "dev"
Dynamic: license-file
